NeuroParser.so
NeuroParser-0.0.6.dist-info/METADATA
NeuroParser-0.0.6.dist-info/WHEEL
NeuroParser-0.0.6.dist-info/top_level.txt
NeuroParser-0.0.6.dist-info/RECORD
