Metadata-Version: 2.1
Name: NeuroParser
Version: 0.0.6
Summary: Pinaps pybindings for improved performanced EEG parsing.
Home-page: UNKNOWN
Author: Harri Renney
Author-email: harri.renney@blino.co.uk
License: UNKNOWN
Platform: UNKNOWN
